[{"province":"内蒙古自治区","city":"乌兰察布市","area":"化德县","name":"金三角邮政支局","code":"013350","address":"内蒙古自治区乌兰察布市化德县长顺镇金三角路","phone":"0474-7907005"},{"province":"内蒙古自治区","city":"乌兰察布市","area":"化德县","name":"长顺街邮政支局","code":"013350","address":"内蒙古自治区乌兰察布市化德县长顺镇长顺西街3号","phone":"0474-7903804"},{"province":"内蒙古自治区","city":"乌兰察布市","area":"化德县","name":"知青路邮政支局","code":"013350","address":"内蒙古自治区乌兰察布市化德县长顺镇知青路","phone":"0474-7907129"},{"province":"内蒙古自治区","city":"乌兰察布市","area":"化德县","name":"长顺街邮政支局","code":"013350","address":"内蒙古自治区乌兰察布市化德县长顺镇长顺西街3号","phone":"0474-7903804"},{"province":"内蒙古自治区","city":"乌兰察布市","area":"化德县","name":"知青路邮政支局","code":"013350","address":"内蒙古自治区乌兰察布市化德县长顺镇知青路","phone":"0474-7907129"}]