[{"province":"山西省","city":"晋城市","area":"晋城市","name":"泽州路邮政支局","code":"048026","address":"晋城市泽州路1782号","phone":"0356-2027144"},{"province":"山西省","city":"晋城市","area":"晋城市","name":"开发区邮政支局","code":"048026","address":"区兰花路与红星街交叉口缔景皇冠大酒店一","phone":"13903560204"},{"province":"山西省","city":"晋城市","area":"晋城市","name":"文昌东街邮政支局","code":"048026","address":"晋城市文昌东街凤鸣小区11栋8号门面房","phone":"17735662173"},{"province":"山西省","city":"晋城市","area":"晋城市","name":"太行北路邮政支局","code":"048026","address":"晋城市太行路北段1392号","phone":"0356-2038359"}]