[{"province":"河北省","city":"石家庄市","area":"桥西区","name":"邮电园邮政支局","code":"050021","address":"河北省石家庄市桥西区东风路126号","phone":"13784337019"},{"province":"河北省","city":"石家庄市","area":"桥西区","name":"邮电园邮政支局","code":"050021","address":"河北省石家庄市桥西区东风路126号","phone":"13784337019"},{"province":"河北省","city":"石家庄市","area":"裕华区","name":"槐中邮政支局","code":"050021","address":"石家庄市槐中路113号","phone":"0311-86011230"},{"province":"河北省","city":"石家庄市","area":"裕华区","name":"槐中邮政支局","code":"050021","address":"石家庄市槐中路113号","phone":"0311-86011230"}]