[{"province":"河北省","city":"石家庄市","area":"井陉矿区","name":"中纬路邮政支局","code":"050100","address":"石家庄市矿区中纬路7号","phone":"13931156827"},{"province":"河北省","city":"石家庄市","area":"井陉矿区","name":"横涧邮政所","code":"050100","address":"河北省石家庄市井陉矿区红房街20号","phone":"13102869318"},{"province":"河北省","city":"石家庄市","area":"井陉矿区","name":"凤山邮政所","code":"050100","address":"河北省石家庄市井陉矿区凤山镇杨家沟村云风路5号","phone":"13931156827"},{"province":"河北省","city":"石家庄市","area":"井陉矿区","name":"贾庄邮政支局","code":"050100","address":"河北省石家庄市井陉矿区贾庄镇贾庄村马家南台街5号","phone":"13931156827"}]