[{"province":"河北省","city":"石家庄市","area":"赞皇县","name":"赞皇龙门邮政代办所","code":"051230","address":"河北省石家庄市赞皇县龙门乡西龙门村","phone":"15373671356"},{"province":"河北省","city":"石家庄市","area":"赞皇县","name":"赞皇南清河邮政代办所","code":"051230","address":"河北省石家庄市赞皇县南清河乡南清河村","phone":"15690366521"},{"province":"河北省","city":"石家庄市","area":"赞皇县","name":"赞皇龙门邮政代办所","code":"051230","address":"河北省石家庄市赞皇县龙门乡西龙门村","phone":"15373671356"},{"province":"河北省","city":"石家庄市","area":"赞皇县","name":"赞皇阳泽邮政代办所","code":"051230","address":"河北省石家庄市赞皇县阳泽乡西阳泽村","phone":"13473430683"},{"province":"河北省","city":"石家庄市","area":"赞皇县","name":"赞皇县新开街邮政支局","code":"051230","address":"河北省石家庄市赞皇县城关镇唐相街110号","phone":"0311-84222144"},{"province":"河北省","city":"石家庄市","area":"赞皇县","name":"赞皇南清河邮政代办所","code":"051230","address":"河北省石家庄市赞皇县南清河乡南清河村","phone":"15690366521"}]