[{"province":"河北省","city":"衡水市","area":"冀州区","name":"徐家庄邮政所","code":"053299","address":"河北省衡水市冀州区徐庄乡徐庄","phone":"13833806288"},{"province":"河北省","city":"衡水市","area":"冀州区","name":"魏屯邮政支局","code":"053299","address":"衡水市冀州区魏家屯镇魏屯村","phone":"0318-8964621"},{"province":"河北省","city":"衡水市","area":"冀州区","name":"小寨邮政所","code":"053299","address":"衡水市冀州区小寨乡小寨村","phone":"0318-8919215"},{"province":"河北省","city":"衡水市","area":"冀州区","name":"信都路邮政支局","code":"053299","address":"衡水市冀州区信都西路445号","phone":"0318-8698621"}]