[{"province":"河北省","city":"沧州市","area":"献县","name":"南河头邮政代办所","code":"062250","address":"河北沧州献县南河头南河头计生站西侧","phone":"15833171066"},{"province":"河北省","city":"沧州市","area":"献县","name":"张村邮政支局","code":"062250","address":"张村乡中街5号","phone":"0317-4671040"},{"province":"河北省","city":"沧州市","area":"献县","name":"小平王邮政代办所","code":"062250","address":"河北沧州献县小平王乡小平王村","phone":"13623272283"},{"province":"河北省","city":"沧州市","area":"献县","name":"张村邮政支局","code":"062250","address":"张村乡中街5号","phone":"0317-4671040"},{"province":"河北省","city":"沧州市","area":"献县","name":"小平王邮政代办所","code":"062250","address":"河北沧州献县小平王乡小平王村","phone":"13623272283"},{"province":"河北省","city":"沧州市","area":"献县","name":"小平王邮政代办所","code":"062250","address":"河北沧州献县小平王乡小平王村","phone":"13623272283"},{"province":"河北省","city":"沧州市","area":"献县","name":"张村邮政支局","code":"062250","address":"张村乡中街5号","phone":"0317-4671040"}]