[{"province":"河北省","city":"秦皇岛市","area":"海港区","name":"燕山大街邮政支局","code":"066001","address":"秦皇岛市海港区燕山大街26号","phone":"0335-3065431"},{"province":"河北省","city":"秦皇岛市","area":"海港区","name":"建国路邮政支局","code":"066001","address":"秦皇岛市海港区燕山大街与建国路交叉口","phone":"0335-3618066"},{"province":"河北省","city":"秦皇岛市","area":"海港区","name":"文化路邮政支局","code":"066001","address":"秦皇岛市海港区文化路298号","phone":"0335-3858072"},{"province":"河北省","city":"秦皇岛市","area":"海港区","name":"火车站邮政支局","code":"066001","address":"秦皇岛市海港区迎宾路","phone":"0335-3618062"},{"province":"河北省","city":"秦皇岛市","area":"海港区","name":"燕山大街邮政支局","code":"066001","address":"秦皇岛市海港区燕山大街26号","phone":"0335-3065431"},{"province":"河北省","city":"秦皇岛市","area":"海港区","name":"建国路邮政支局","code":"066001","address":"秦皇岛市海港区燕山大街与建国路交叉口","phone":"0335-3618066"},{"province":"河北省","city":"秦皇岛市","area":"海港区","name":"文化路邮政支局","code":"066001","address":"秦皇岛市海港区文化路298号","phone":"0335-3858072"},{"province":"河北省","city":"秦皇岛市","area":"海港区","name":"火车站邮政支局","code":"066001","address":"秦皇岛市海港区迎宾路","phone":"0335-3618062"}]