[{"province":"河北省","city":"保定市","area":"莲池区","name":"双胜街邮政支局","code":"071028","address":"河北省保定市双胜街315-2号","phone":"0312-5026158"},{"province":"河北省","city":"保定市","area":"莲池区","name":"合作路邮政支局","code":"071028","address":"河北省保定市五四东路河北大学东行","phone":"0312-5061320"},{"province":"河北省","city":"保定市","area":"莲池区","name":"韩庄邮政所","code":"071028","address":"河北保定竞秀韩庄","phone":"0312-3330525"},{"province":"河北省","city":"保定市","area":"竞秀区","name":"贤台邮政所","code":"071028","address":"河北保定竞秀贤台","phone":"0312-3330265"},{"province":"河北省","city":"保定市","area":"莲池区","name":"七一东路邮政支局","code":"071028","address":"河北省保定市七一东路416号","phone":"0312-5993208"}]