[{"province":"河北省","city":"张家口市","area":"怀安县","name":"工业街邮政支局","code":"076150","address":"怀安县柴沟堡镇工业街1号","phone":"0313-7810185"},{"province":"河北省","city":"张家口市","area":"怀安县","name":"东大街邮政支局","code":"076150","address":"怀安县柴沟堡镇水口街","phone":"0313-7826100"},{"province":"河北省","city":"张家口市","area":"怀安县","name":"西沙城邮政所","code":"076150","address":"河北张家口怀安西沙城","phone":"18713335903"},{"province":"河北省","city":"张家口市","area":"怀安县","name":"渡口堡邮政所","code":"076150","address":"河北张家口怀安县渡口堡","phone":"15031349344"},{"province":"河北省","city":"张家口市","area":"怀安县","name":"第六屯邮政所","code":"076150","address":"河北张家口怀安第六屯","phone":"15132350240"}]