[{"province":"辽宁省","city":"沈阳市","area":"沈河区","name":"中街路邮政支局","code":"110011","address":"辽宁省沈阳市沈河区皇城街道朝阳街89甲18号18门","phone":"024-24846151"},{"province":"辽宁省","city":"沈阳市","area":"沈河区","name":"大南街邮政所","code":"110011","address":"辽宁省沈阳市沈河区大南街道大南街215号","phone":"024-24812486"},{"province":"辽宁省","city":"沈阳市","area":"沈河区","name":"小南街邮政支局","code":"110011","address":"辽宁省沈阳市沈河区滨河街道南乐郊路48甲1号","phone":"024-84112415"},{"province":"辽宁省","city":"沈阳市","area":"沈河区","name":"南通天街邮政所","code":"110011","address":"辽宁省沈阳市沈河区滨河街道南通天街20号","phone":"18940267037"}]