[{"province":"辽宁省","city":"大连市","area":"普兰店区","name":"中心路邮政支局","code":"116299","address":"辽宁省大连市普兰店区丰荣街道中心路170-3号","phone":"0411-83137111"},{"province":"辽宁省","city":"大连市","area":"普兰店区","name":"丰荣邮政支局","code":"116299","address":"辽宁省大连市普兰店区丰荣街道办事处古城村413号","phone":"0411-83129755"},{"province":"辽宁省","city":"大连市","area":"普兰店区","name":"铁西邮政支局","code":"116299","address":"辽宁省大连市普兰店区铁西街道西工路41-3","phone":"0411-83190850"},{"province":"辽宁省","city":"大连市","area":"普兰店区","name":"鼎盛邮政支局","code":"116299","address":"辽宁省大连市普兰店区太平街道办事处世纪路西段308-1号","phone":"0411-83387987"},{"province":"辽宁省","city":"大连市","area":"普兰店区","name":"普兰店邮政支局","code":"116299","address":"辽宁省大连市普兰店区太平街道办事处南山路92号","phone":"0411-83112312"}]