[{"province":"辽宁省","city":"本溪市","area":"本溪满族自治县","name":"本溪县邮政支局","code":"117199","address":"辽宁省本溪市本溪满族自治县小市镇育才街139号","phone":"024-46205018"},{"province":"辽宁省","city":"本溪市","area":"本溪满族自治县","name":"市场邮政支局","code":"117199","address":"辽宁省本溪市本溪满族自治县小市镇春光路230-3号","phone":"024-46824586"},{"province":"辽宁省","city":"本溪市","area":"本溪满族自治县","name":"市场邮政支局","code":"117199","address":"辽宁省本溪市本溪满族自治县小市镇春光路230-3号","phone":"024-46824586"},{"province":"辽宁省","city":"本溪市","area":"本溪满族自治县","name":"市场邮政支局","code":"117199","address":"辽宁省本溪市本溪满族自治县小市镇春光路230-3号","phone":"024-46824586"}]