[{"province":"辽宁省","city":"阜新市","area":"阜新蒙古族自治县","name":"阜蒙县大五支局","code":"123137","address":"阜蒙县大五家子乡本街","phone":"0418-8130506"},{"province":"辽宁省","city":"阜新市","area":"阜新蒙古族自治县","name":"阜蒙县大五支局","code":"123137","address":"阜蒙县大五家子乡本街","phone":"0418-8130506"},{"province":"辽宁省","city":"阜新市","area":"阜新蒙古族自治县","name":"阜蒙县大五支局","code":"123137","address":"阜蒙县大五家子乡本街","phone":"0418-8130506"},{"province":"辽宁省","city":"阜新市","area":"阜新蒙古族自治县","name":"阜蒙县大五支局","code":"123137","address":"阜蒙县大五家子乡本街","phone":"0418-8130506"}]