[{"province":"辽宁省","city":"葫芦岛市","area":"连山区","name":"葫芦岛市群英路邮政所","code":"125001","address":"葫芦岛市连山区群英路F楼14号门市房","phone":"0429-2126631"},{"province":"辽宁省","city":"葫芦岛市","area":"连山区","name":"葫芦岛市民安邮政所","code":"125001","address":"葫芦岛市连山区民安路","phone":"0429-2131700"},{"province":"辽宁省","city":"葫芦岛市","area":"连山区","name":"葫芦岛市化工邮政所","code":"125001","address":"葫芦岛市连山区化工11区24号楼","phone":"0429-2901562"},{"province":"辽宁省","city":"葫芦岛市","area":"连山区","name":"葫芦岛市解放路邮政所","code":"125001","address":"葫芦岛市连山区解放路海飞学院对过","phone":"0429-2951415"},{"province":"辽宁省","city":"葫芦岛市","area":"连山区","name":"葫芦岛市滨河路邮政支局","code":"125001","address":"葫芦岛市连山区滨河路","phone":"0429-2911598"},{"province":"辽宁省","city":"葫芦岛市","area":"连山区","name":"葫芦岛市石油邮政支局","code":"125001","address":"山海滨路第5-44(D-1)幢A号、B","phone":"0429-3745100"},{"province":"辽宁省","city":"葫芦岛市","area":"连山区","name":"葫芦岛市兴盛邮政所","code":"125001","address":"葫芦岛市连山区兴盛街17号","phone":"0429-2152732"},{"province":"辽宁省","city":"葫芦岛市","area":"连山区","name":"葫芦岛市中央大街邮政支局","code":"125001","address":"葫芦岛市连山区中央大街12号","phone":"0429-2121737"}]