[{"province":"吉林省","city":"长春市","area":"二道区","name":"东齿邮政支局","code":"130102","address":"长春市兴隆大路6333号","phone":"0431-84591187"},{"province":"吉林省","city":"长春市","area":"二道区","name":"兴隆山邮政支局","code":"130102","address":"长春市兴隆山镇兴隆丽景城(与金融网点相邻","phone":"17767762372"},{"province":"吉林省","city":"长春市","area":"宽城区","name":"北工大邮政所","code":"130102","address":"吉林省长春市高新北区北远达大街3000","phone":"13278561662"},{"province":"吉林省","city":"长春市","area":"宽城区","name":"奋进邮政所","code":"130102","address":"长春市奋进乡福源西街兴花园A区","phone":"15004304691"},{"province":"吉林省","city":"长春市","area":"宽城区","name":"福源街邮政支局","code":"130102","address":"长春市高新北区天朗·蔚蓝北府二期G2幢101号房","phone":"0431-84951249"}]