[{"province":"吉林省","city":"四平市","area":"铁东区","name":"石岭子邮政支局","code":"136001","address":"四平市铁东区石岭子镇","phone":"0434-5462497"},{"province":"吉林省","city":"四平市","area":"铁东区","name":"铁东邮政支局","code":"136001","address":"四平市铁东区北一纬六七马路之间","phone":"0434-3528272"},{"province":"吉林省","city":"四平市","area":"铁东区","name":"九马路邮政支局","code":"136001","address":"吉林省四平市平东大街爱平委1层101号","phone":"0434-3389710"},{"province":"吉林省","city":"四平市","area":"铁东区","name":"中央东路邮政支局","code":"136001","address":"四平市铁东区中央东路1464号","phone":"0434-3512362"},{"province":"吉林省","city":"四平市","area":"铁东区","name":"南一马路邮政支局","code":"136001","address":"四平市铁东区南一经街969号","phone":"0434-3127757"},{"province":"吉林省","city":"四平市","area":"铁东区","name":"大鹰广场邮政支局","code":"136001","address":"四平市铁东区中央东路一中对面","phone":"0434-3351596"},{"province":"吉林省","city":"四平市","area":"铁东区","name":"叶赫邮政支局","code":"136001","address":"四平市铁东区叶赫镇","phone":"0434-3566218"},{"province":"吉林省","city":"四平市","area":"铁东区","name":"大庙邮政支局","code":"136001","address":"铁东区中华新城29号楼104号","phone":"0434-3333454"},{"province":"吉林省","city":"四平市","area":"铁东区","name":"城东乡邮政支局","code":"136001","address":"合力村","phone":"0434-3225538"},{"province":"吉林省","city":"四平市","area":"铁东区","name":"昊华邮政支局","code":"136001","address":"西北门街芳草委海银小区4号楼一层116","phone":"0434-3517121"}]