[{"province":"上海市","city":"上海市","area":"闵行区","name":"沪闵路邮政支局","code":"200240","address":"沪闵路118号","phone":"021-64356264"},{"province":"上海市","city":"上海市","area":"闵行区","name":"宾川路邮政所","code":"200240","address":"闵行区宾川路412号","phone":"021-64306418"},{"province":"上海市","city":"上海市","area":"闵行区","name":"红旗新村邮政所","code":"200240","address":"闵行区景谷路146号","phone":"021-64307534"},{"province":"上海市","city":"上海市","area":"闵行区","name":"江川路邮政所","code":"200240","address":"闵行区沪闵路269号-40","phone":"021-34752201"},{"province":"上海市","city":"上海市","area":"闵行区","name":"交大二部邮政所","code":"200240","address":"闵行区东川路800号","phone":"021-54742986"}]