[{"province":"上海市","city":"上海市","area":"闵行区","name":"田园邮政支局","code":"201108","address":"闵行区都市路3677号","phone":"021-64584315"},{"province":"上海市","city":"上海市","area":"闵行区","name":"曹行邮政所","code":"201108","address":"闵行区曹建西路237弄","phone":"021-64971944"},{"province":"上海市","city":"上海市","area":"闵行区","name":"颛建路邮政所","code":"201108","address":"上海市上海市闵行区颛兴路108号","phone":"021-54312065"},{"province":"上海市","city":"上海市","area":"闵行区","name":"申北路邮政所","code":"201108","address":"闵行区申北路272号","phone":"021-54392120"},{"province":"上海市","city":"上海市","area":"闵行区","name":"君莲邮政所","code":"201108","address":"闵行区颛桥镇春都路420号101、103、104","phone":"021-54710005"}]