[{"province":"江苏省","city":"徐州市","area":"睢宁县","name":"西郊邮政支局","code":"221200","address":"江苏省徐州市睢宁县八一西路农工办综合楼102-105","phone":"0516-88332299"},{"province":"江苏省","city":"徐州市","area":"睢宁县","name":"睢城邮政支局","code":"221200","address":"江苏省徐州市睢宁县睢宁县元府东路教师公寓4#楼东4单元东9","phone":"0516-88391231"},{"province":"江苏省","city":"徐州市","area":"睢宁县","name":"人民路邮政支局","code":"221200","address":"徐州市睢宁县人民路泰和医院东","phone":"0516-88384999"},{"province":"江苏省","city":"徐州市","area":"睢宁县","name":"新市街邮政支局","code":"221200","address":"徐州市睢宁县新市街3号","phone":"0516-88333754"},{"province":"江苏省","city":"徐州市","area":"睢宁县","name":"中山邮政支局","code":"221200","address":"江苏省徐州市睢宁县新市街商城1号楼1-116-118号","phone":"0516-88333700"},{"province":"江苏省","city":"徐州市","area":"睢宁县","name":"八一路邮政支局","code":"221200","address":"江苏省徐州市睢宁县八一东路22号医药公司综合楼1010-1011室","phone":"0516-88309726"},{"province":"江苏省","city":"徐州市","area":"睢宁县","name":"红叶邮政支局","code":"221200","address":"江苏省徐州市睢宁县红叶北路文化城2号楼东2","phone":"0516-88360959"}]