[{"province":"江苏省","city":"盐城市","area":"射阳县","name":"射阳红旗路邮政支局","code":"224300","address":"射阳县合德镇红旗路4-1号","phone":"0515-82352206"},{"province":"江苏省","city":"盐城市","area":"射阳县","name":"射阳人民西路邮政支局","code":"224300","address":"射阳县合德镇人民西路50号","phone":"0515-82380030"},{"province":"江苏省","city":"盐城市","area":"射阳县","name":"射阳双山北路邮政支局","code":"224300","address":"射阳县合德镇双山北路与红旗西路交界路口","phone":"0515-82376206"},{"province":"江苏省","city":"盐城市","area":"射阳县","name":"射阳朝阳邮政支局","code":"224300","address":"射阳县合德镇朝阳街40号","phone":"0515-82322411"}]