[{"province":"浙江省","city":"衢州市","area":"江山市","name":"江山市塘源口邮政代办所","code":"324106","address":"浙江衢州江山塘源口乡","phone":"13867003078"},{"province":"浙江省","city":"衢州市","area":"江山市","name":"江山市双溪口邮政代办所","code":"324106","address":"浙江衢州江山张村乡双溪口村42号","phone":"15957041998"},{"province":"浙江省","city":"衢州市","area":"江山市","name":"江山市张村代办所","code":"324106","address":"浙江衢州江山市张村乡秀峰路61号","phone":"15057041913"},{"province":"浙江省","city":"衢州市","area":"江山市","name":"江山市双溪口邮政代办所","code":"324106","address":"浙江衢州江山张村乡双溪口村42号","phone":"15957041998"},{"province":"浙江省","city":"衢州市","area":"江山市","name":"江山市张村代办所","code":"324106","address":"浙江衢州江山市张村乡秀峰路61号","phone":"15057041913"},{"province":"浙江省","city":"衢州市","area":"江山市","name":"江山市张村代办所","code":"324106","address":"浙江衢州江山市张村乡秀峰路61号","phone":"15057041913"},{"province":"浙江省","city":"衢州市","area":"江山市","name":"江山市塘源口邮政代办所","code":"324106","address":"浙江衢州江山塘源口乡","phone":"13867003078"},{"province":"浙江省","city":"衢州市","area":"江山市","name":"江山市双溪口邮政代办所","code":"324106","address":"浙江衢州江山张村乡双溪口村42号","phone":"15957041998"}]