[{"province":"浙江省","city":"温州市","area":"苍南县","name":"霞关邮政所","code":"325809","address":"浙江省温州市苍南县霞关镇望海路17号","phone":"0577-59866969"},{"province":"浙江省","city":"温州市","area":"苍南县","name":"岱岭邮政所","code":"325809","address":"浙江温州苍南岱岭乡杨家边村21","phone":"0577-64661555"},{"province":"浙江省","city":"温州市","area":"苍南县","name":"霞关邮政所","code":"325809","address":"浙江省温州市苍南县霞关镇望海路17号","phone":"0577-59866969"},{"province":"浙江省","city":"温州市","area":"苍南县","name":"岱岭邮政所","code":"325809","address":"浙江温州苍南岱岭乡杨家边村21","phone":"0577-64661555"},{"province":"浙江省","city":"温州市","area":"苍南县","name":"岱岭邮政所","code":"325809","address":"浙江温州苍南岱岭乡杨家边村21","phone":"0577-64661555"}]