[{"province":"江西省","city":"南昌市","area":"红谷滩区","name":"东华理工枫林邮政所（暂停）","code":"330013","address":"南昌市经济技术开发区枫林大街892号东华理工大学枫林校区内","phone":"13576099965"},{"province":"江西省","city":"南昌市","area":"红谷滩区","name":"东华理工邮政所（暂停）","code":"330013","address":"江西省南昌市经济技术开发区广兰大道418号","phone":"13576099965"},{"province":"江西省","city":"南昌市","area":"红谷滩区","name":"司法警官学院邮政所（暂停）","code":"330013","address":"江西省南昌市经济技术开发区长青路76号","phone":"13576099965"},{"province":"江西省","city":"南昌市","area":"红谷滩区","name":"江西财大邮政支局","code":"330013","address":"南昌市昌经济技术开发区开发区双港路85号","phone":"0791-88820472"},{"province":"江西省","city":"南昌市","area":"红谷滩区","name":"双港邮政所","code":"330013","address":"江西省南昌市下罗双港路603厂大门口","phone":"18070138590"},{"province":"江西省","city":"南昌市","area":"红谷滩区","name":"下罗邮政所","code":"330013","address":"江西省南昌市庐山南大道2789号枫庐新天地一栋7、8、9号","phone":"13576271991"}]