[{"province":"江西省","city":"宜春市","area":"奉新县","name":"城南邮政所","code":"330799","address":"江西省宜春市奉新县书院路1号","phone":"0795-7183906"},{"province":"江西省","city":"宜春市","area":"奉新县","name":"擎天邮政所","code":"330799","address":"江西省宜春市奉新县冯川东路56号","phone":"15970503876"},{"province":"江西省","city":"宜春市","area":"奉新县","name":"狮山邮政所","code":"330799","address":"江西省宜春市奉新县狮山大道216号","phone":"13970570399"},{"province":"江西省","city":"宜春市","area":"奉新县","name":"大楼邮政所","code":"330799","address":"奉新县奉新中大道340号","phone":"15879590288"}]