[{"province":"福建省","city":"厦门市","area":"海沧区","name":"石塘邮政支局","code":"361026","address":"福建省厦门市海沧区海富路250-4号","phone":"0592-6052046"},{"province":"福建省","city":"厦门市","area":"海沧区","name":"海沧邮政所","code":"361026","address":"福建省厦门市海沧区大路头76号","phone":"0592-6081200"},{"province":"福建省","city":"厦门市","area":"海沧区","name":"嵩屿邮政支局","code":"361026","address":"福建省厦门市海沧区嵩屿南二路82号","phone":"0592-6081243"},{"province":"福建省","city":"厦门市","area":"海沧区","name":"鼓浪湾邮政支局","code":"361026","address":"福建省厦门市海沧区滨湖路1904号","phone":"0592-6532556"}]