[{"province":"湖南省","city":"益阳市","area":"安化县","name":"电信邮政支局","code":"413500","address":"湖南省益阳市安化县东坪镇解放路","phone":"0737-7223332"},{"province":"湖南省","city":"益阳市","area":"安化县","name":"迎春路邮政支局","code":"413500","address":"湖南省益阳市安化县东坪镇迎春路","phone":"0737-7867951"},{"province":"湖南省","city":"益阳市","area":"安化县","name":"南金邮政所","code":"413500","address":"湖南省益阳市安化县南金乡南金村","phone":"0737-7561218"},{"province":"湖南省","city":"益阳市","area":"安化县","name":"迎春路邮政支局","code":"413500","address":"湖南省益阳市安化县东坪镇迎春路","phone":"0737-7867951"},{"province":"湖南省","city":"益阳市","area":"安化县","name":"南金邮政所","code":"413500","address":"湖南省益阳市安化县南金乡南金村","phone":"0737-7561218"},{"province":"湖南省","city":"益阳市","area":"安化县","name":"南金邮政所","code":"413500","address":"湖南省益阳市安化县南金乡南金村","phone":"0737-7561218"}]