[{"province":"湖南省","city":"岳阳市","area":"平江县","name":"长寿邮政支局","code":"414506","address":"平江县长寿镇","phone":"0730-6671002"},{"province":"湖南省","city":"岳阳市","area":"平江县","name":"伍市工业园邮政所","code":"414506","address":"平江县伍市工业园","phone":"18673082228"},{"province":"湖南省","city":"岳阳市","area":"平江县","name":"黄金洞乡邮政所","code":"414506","address":"平江县黄金洞乡","phone":"13786036411"},{"province":"湖南省","city":"岳阳市","area":"平江县","name":"南桥乡邮政所","code":"414506","address":"平江县南桥乡","phone":"13341309180"},{"province":"湖南省","city":"岳阳市","area":"平江县","name":"木金乡邮政所","code":"414506","address":"平江县木金乡","phone":"18573040208"}]