[{"province":"湖南省","city":"湘西土家族苗族自治州","area":"吉首市","name":"社塘坡邮政所","code":"416007","address":"湖南省吉首市乾州街道强虎村","phone":"17774313146"},{"province":"湖南省","city":"湘西土家族苗族自治州","area":"吉首市","name":"双塘邮政所","code":"416007","address":"湖南省吉首市双塘街道办事处院内","phone":"18074312213"},{"province":"湖南省","city":"湘西土家族苗族自治州","area":"吉首市","name":"社塘坡邮政所","code":"416007","address":"湖南省吉首市乾州街道强虎村","phone":"17774313146"},{"province":"湖南省","city":"湘西土家族苗族自治州","area":"吉首市","name":"双塘邮政所","code":"416007","address":"湖南省吉首市双塘街道办事处院内","phone":"18074312213"}]