[{"province":"湖南省","city":"衡阳市","area":"耒阳市","name":"耒阳市城北路所","code":"421800","address":"耒阳市城北中路110号","phone":"0734-4320723"},{"province":"湖南省","city":"衡阳市","area":"耒阳市","name":"耒阳市城北路所","code":"421800","address":"耒阳市城北中路110号","phone":"0734-4320723"},{"province":"湖南省","city":"衡阳市","area":"耒阳市","name":"耒阳市广场所","code":"421800","address":"耒阳市蔡子池街道五一东路3号","phone":"0734-4331010"},{"province":"湖南省","city":"衡阳市","area":"耒阳市","name":"耒阳市城北路所","code":"421800","address":"耒阳市城北中路110号","phone":"0734-4320723"},{"province":"湖南省","city":"衡阳市","area":"耒阳市","name":"耒阳市城北路所","code":"421800","address":"耒阳市城北中路110号","phone":"0734-4320723"},{"province":"湖南省","city":"衡阳市","area":"耒阳市","name":"耒阳市城北路所","code":"421800","address":"耒阳市城北中路110号","phone":"0734-4320723"}]