[{"province":"湖北省","city":"武汉市","area":"硚口区","name":"桥口路邮政支局","code":"430033","address":"中山大道33号","phone":"15827309191"},{"province":"湖北省","city":"武汉市","area":"硚口区","name":"汉西三路邮政所","code":"430033","address":"汉西三路81号","phone":"15071045234"},{"province":"湖北省","city":"武汉市","area":"硚口区","name":"海校邮政所","code":"430033","address":"海军工程大学院内","phone":"13476009276"},{"province":"湖北省","city":"武汉市","area":"硚口区","name":"长风路邮政所","code":"430033","address":"硚口区长风路华生汉口城市广场B区B335","phone":"19908650605"},{"province":"湖北省","city":"武汉市","area":"硚口区","name":"仁寿路邮政所","code":"430033","address":"解放大道340号","phone":"13476009276"}]