[{"province":"山西省","city":"长治市","area":"潞州区","name":"八一广场支局","code":"46011","address":"山西省长治市八一广场西南角（距邮储银行100米内）","phone":"0355-2041185"},{"province":"山西省","city":"长治市","area":"潞州区","name":"城北西街邮政所","code":"46011","address":"山西省长治市城北西街118号1号楼32号","phone":"0355-2611997"},{"province":"山西省","city":"长治市","area":"潞州区","name":"八一广场支局","code":"46011","address":"山西省长治市八一广场西南角（距邮储银行100米内）","phone":"0355-2041185"},{"province":"山西省","city":"长治市","area":"潞州区","name":"城北西街邮政所","code":"46011","address":"山西省长治市城北西街118号1号楼32号","phone":"0355-2611997"}]