[{"province":"广东省","city":"广州市","area":"天河区","name":"体育东路邮政支局","code":"510620","address":"广东省广州市天河区体育东路7号","phone":"18122031196"},{"province":"广东省","city":"广州市","area":"天河区","name":"天河东邮政支局","code":"510620","address":"广州市天河区天河东路155号骏源大厦首层","phone":"020-38851099"},{"province":"广东省","city":"广州市","area":"天河区","name":"天河南邮政支局","code":"510620","address":"广东省广州市天河区天河南二路8号建丰大厦首层","phone":"020-87596511"},{"province":"广东省","city":"广州市","area":"天河区","name":"东塔邮政支局","code":"510620","address":"广州市天河区珠江东路6号101","phone":"020-38803291"}]