[{"province":"广东省","city":"深圳市","area":"福田区","name":"创意园邮政所","code":"518048","address":"广东省深圳市福田区福强路文化创意园A馆西边1楼A01","phone":"0755-83801210"},{"province":"广东省","city":"深圳市","area":"福田区","name":"沙咀邮政支局","code":"518048","address":"广东省深圳市福田区福强路文化创意园A馆一楼","phone":"0755-25982160"},{"province":"广东省","city":"深圳市","area":"福田区","name":"明月邮政所","code":"518048","address":"深圳市福田区明月花园2栋首层101号","phone":"0755-83830432"},{"province":"广东省","city":"深圳市","area":"福田区","name":"宜增邮政所","code":"518048","address":"广东省深圳市福田区沙尾东村300-101","phone":"0755-83591588"},{"province":"广东省","city":"深圳市","area":"福田区","name":"福田口岸邮政所","code":"518048","address":"广东省深圳市福田区福田街道裕亨路3号金地名津广场裙楼1楼84号","phone":"0755-82131691"},{"province":"广东省","city":"深圳市","area":"福田区","name":"石厦邮政所","code":"518048","address":"深圳市福田区沙头街道石厦村110栋104","phone":"0755-83805877"},{"province":"广东省","city":"深圳市","area":"福田区","name":"新顺邮政所","code":"518048","address":"广东深圳福田沙头街道新洲中心村80栋1号铺","phone":"0755-83405585"},{"province":"广东省","city":"深圳市","area":"福田区","name":"新福邮政所","code":"518048","address":"广东省深圳市福田区沙头街道滨河路新洲村新洲一街72号","phone":"0755-83414418"},{"province":"广东省","city":"深圳市","area":"福田区","name":"桂花苑邮政所","code":"518048","address":"广东省深圳市福田区福保街道桂花路桂花苑2栋8号","phone":"0755-23484889"}]