[{"province":"广东省","city":"深圳市","area":"宝安区","name":"旋风邮政便民服务点","code":"518103","address":"深圳市宝安区福海街道新和社区富桥三区一期宿舍B2栋101-105","phone":"18588430891"},{"province":"广东省","city":"深圳市","area":"宝安区","name":"旭利邮政便民服务点","code":"518103","address":"深圳市宝安区福海街道桥头荔园路26号","phone":"13823378861"},{"province":"广东省","city":"深圳市","area":"宝安区","name":"春红邮政便民服务点","code":"518103","address":"深圳市宝安区福海街道新和社区二区十六巷6号104","phone":"15818560018"},{"province":"广东省","city":"深圳市","area":"宝安区","name":"仕泉邮政便民服务点","code":"518103","address":"深圳市宝安区福海街道塘尾社区塘尾十三区十三巷8－2号","phone":"13713862813"},{"province":"广东省","city":"深圳市","area":"宝安区","name":"旋风邮政便民服务点","code":"518103","address":"深圳市宝安区福海街道新和社区富桥三区一期宿舍B2栋101-105","phone":"18588430891"},{"province":"广东省","city":"深圳市","area":"宝安区","name":"恒之邮邮政便民服务点","code":"518103","address":"深圳市宝安区福海街道新和社区西一巷1-1号101","phone":"15817267469"},{"province":"广东省","city":"深圳市","area":"宝安区","name":"海军邮政便民服务点","code":"518103","address":"深圳市宝安区福海街道和平社区玻璃围新村北六巷15－1号","phone":"13713799577"},{"province":"广东省","city":"深圳市","area":"宝安区","name":"旋风邮政便民服务点","code":"518103","address":"深圳市宝安区福海街道新和社区富桥三区一期宿舍B2栋101-105","phone":"18588430891"},{"province":"广东省","city":"深圳市","area":"宝安区","name":"仕泉邮政便民服务点","code":"518103","address":"深圳市宝安区福海街道塘尾社区塘尾十三区十三巷8－2号","phone":"13713862813"},{"province":"广东省","city":"深圳市","area":"宝安区","name":"宝丽邮政便民服务点","code":"518103","address":"深圳市宝安区福海街道稔田社区新区167号新区147号","phone":"13822607856"},{"province":"广东省","city":"深圳市","area":"宝安区","name":"兴旺邮政便民服务点","code":"518103","address":"深圳市宝安区福海街道和平社区同益新村东一巷8号","phone":"15712132108"},{"province":"广东省","city":"深圳市","area":"宝安区","name":"旭利邮政便民服务点","code":"518103","address":"深圳市宝安区福海街道桥头荔园路26号","phone":"13823378861"},{"province":"广东省","city":"深圳市","area":"宝安区","name":"春红邮政便民服务点","code":"518103","address":"深圳市宝安区福海街道新和社区二区十六巷6号104","phone":"15818560018"},{"province":"广东省","city":"深圳市","area":"宝安区","name":"仕泉邮政便民服务点","code":"518103","address":"深圳市宝安区福海街道塘尾社区塘尾十三区十三巷8－2号","phone":"13713862813"},{"province":"广东省","city":"深圳市","area":"宝安区","name":"旋风邮政便民服务点","code":"518103","address":"深圳市宝安区福海街道新和社区富桥三区一期宿舍B2栋101-105","phone":"18588430891"},{"province":"广东省","city":"深圳市","area":"宝安区","name":"恒之邮邮政便民服务点","code":"518103","address":"深圳市宝安区福海街道新和社区西一巷1-1号101","phone":"15817267469"},{"province":"广东省","city":"深圳市","area":"宝安区","name":"海军邮政便民服务点","code":"518103","address":"深圳市宝安区福海街道和平社区玻璃围新村北六巷15－1号","phone":"13713799577"},{"province":"广东省","city":"深圳市","area":"宝安区","name":"春红邮政便民服务点","code":"518103","address":"深圳市宝安区福海街道新和社区二区十六巷6号104","phone":"15818560018"},{"province":"广东省","city":"深圳市","area":"宝安区","name":"旭利邮政便民服务点","code":"518103","address":"深圳市宝安区福海街道桥头荔园路26号","phone":"13823378861"},{"province":"广东省","city":"深圳市","area":"宝安区","name":"宝丽邮政便民服务点","code":"518103","address":"深圳市宝安区福海街道稔田社区新区167号新区147号","phone":"13822607856"},{"province":"广东省","city":"深圳市","area":"宝安区","name":"兴旺邮政便民服务点","code":"518103","address":"深圳市宝安区福海街道和平社区同益新村东一巷8号","phone":"15712132108"},{"province":"广东省","city":"深圳市","area":"宝安区","name":"旭利邮政便民服务点","code":"518103","address":"深圳市宝安区福海街道桥头荔园路26号","phone":"13823378861"},{"province":"广东省","city":"深圳市","area":"宝安区","name":"春红邮政便民服务点","code":"518103","address":"深圳市宝安区福海街道新和社区二区十六巷6号104","phone":"15818560018"},{"province":"广东省","city":"深圳市","area":"宝安区","name":"仕泉邮政便民服务点","code":"518103","address":"深圳市宝安区福海街道塘尾社区塘尾十三区十三巷8－2号","phone":"13713862813"},{"province":"广东省","city":"深圳市","area":"宝安区","name":"旋风邮政便民服务点","code":"518103","address":"深圳市宝安区福海街道新和社区富桥三区一期宿舍B2栋101-105","phone":"18588430891"},{"province":"广东省","city":"深圳市","area":"宝安区","name":"恒之邮邮政便民服务点","code":"518103","address":"深圳市宝安区福海街道新和社区西一巷1-1号101","phone":"15817267469"},{"province":"广东省","city":"深圳市","area":"宝安区","name":"海军邮政便民服务点","code":"518103","address":"深圳市宝安区福海街道和平社区玻璃围新村北六巷15－1号","phone":"13713799577"},{"province":"广东省","city":"深圳市","area":"宝安区","name":"兴旺邮政便民服务点","code":"518103","address":"深圳市宝安区福海街道和平社区同益新村东一巷8号","phone":"15712132108"},{"province":"广东省","city":"深圳市","area":"宝安区","name":"宝丽邮政便民服务点","code":"518103","address":"深圳市宝安区福海街道稔田社区新区167号新区147号","phone":"13822607856"},{"province":"广东省","city":"深圳市","area":"宝安区","name":"宝丽邮政便民服务点","code":"518103","address":"深圳市宝安区福海街道稔田社区新区167号新区147号","phone":"13822607856"},{"province":"广东省","city":"深圳市","area":"宝安区","name":"兴旺邮政便民服务点","code":"518103","address":"深圳市宝安区福海街道和平社区同益新村东一巷8号","phone":"15712132108"},{"province":"广东省","city":"深圳市","area":"宝安区","name":"旭利邮政便民服务点","code":"518103","address":"深圳市宝安区福海街道桥头荔园路26号","phone":"13823378861"},{"province":"广东省","city":"深圳市","area":"宝安区","name":"春红邮政便民服务点","code":"518103","address":"深圳市宝安区福海街道新和社区二区十六巷6号104","phone":"15818560018"},{"province":"广东省","city":"深圳市","area":"宝安区","name":"仕泉邮政便民服务点","code":"518103","address":"深圳市宝安区福海街道塘尾社区塘尾十三区十三巷8－2号","phone":"13713862813"},{"province":"广东省","city":"深圳市","area":"宝安区","name":"旋风邮政便民服务点","code":"518103","address":"深圳市宝安区福海街道新和社区富桥三区一期宿舍B2栋101-105","phone":"18588430891"},{"province":"广东省","city":"深圳市","area":"宝安区","name":"恒之邮邮政便民服务点","code":"518103","address":"深圳市宝安区福海街道新和社区西一巷1-1号101","phone":"15817267469"},{"province":"广东省","city":"深圳市","area":"宝安区","name":"海军邮政便民服务点","code":"518103","address":"深圳市宝安区福海街道和平社区玻璃围新村北六巷15－1号","phone":"13713799577"},{"province":"广东省","city":"深圳市","area":"宝安区","name":"海军邮政便民服务点","code":"518103","address":"深圳市宝安区福海街道和平社区玻璃围新村北六巷15－1号","phone":"13713799577"},{"province":"广东省","city":"深圳市","area":"宝安区","name":"恒之邮邮政便民服务点","code":"518103","address":"深圳市宝安区福海街道新和社区西一巷1-1号101","phone":"15817267469"},{"province":"广东省","city":"深圳市","area":"宝安区","name":"宝丽邮政便民服务点","code":"518103","address":"深圳市宝安区福海街道稔田社区新区167号新区147号","phone":"13822607856"},{"province":"广东省","city":"深圳市","area":"宝安区","name":"兴旺邮政便民服务点","code":"518103","address":"深圳市宝安区福海街道和平社区同益新村东一巷8号","phone":"15712132108"},{"province":"广东省","city":"深圳市","area":"宝安区","name":"旭利邮政便民服务点","code":"518103","address":"深圳市宝安区福海街道桥头荔园路26号","phone":"13823378861"},{"province":"广东省","city":"深圳市","area":"宝安区","name":"春红邮政便民服务点","code":"518103","address":"深圳市宝安区福海街道新和社区二区十六巷6号104","phone":"15818560018"},{"province":"广东省","city":"深圳市","area":"宝安区","name":"仕泉邮政便民服务点","code":"518103","address":"深圳市宝安区福海街道塘尾社区塘尾十三区十三巷8－2号","phone":"13713862813"},{"province":"广东省","city":"深圳市","area":"宝安区","name":"旋风邮政便民服务点","code":"518103","address":"深圳市宝安区福海街道新和社区富桥三区一期宿舍B2栋101-105","phone":"18588430891"},{"province":"广东省","city":"深圳市","area":"宝安区","name":"恒之邮邮政便民服务点","code":"518103","address":"深圳市宝安区福海街道新和社区西一巷1-1号101","phone":"15817267469"},{"province":"广东省","city":"深圳市","area":"宝安区","name":"海军邮政便民服务点","code":"518103","address":"深圳市宝安区福海街道和平社区玻璃围新村北六巷15－1号","phone":"13713799577"},{"province":"广东省","city":"深圳市","area":"宝安区","name":"旋风邮政便民服务点","code":"518103","address":"深圳市宝安区福海街道新和社区富桥三区一期宿舍B2栋101-105","phone":"18588430891"},{"province":"广东省","city":"深圳市","area":"宝安区","name":"仕泉邮政便民服务点","code":"518103","address":"深圳市宝安区福海街道塘尾社区塘尾十三区十三巷8－2号","phone":"13713862813"},{"province":"广东省","city":"深圳市","area":"宝安区","name":"宝丽邮政便民服务点","code":"518103","address":"深圳市宝安区福海街道稔田社区新区167号新区147号","phone":"13822607856"},{"province":"广东省","city":"深圳市","area":"宝安区","name":"兴旺邮政便民服务点","code":"518103","address":"深圳市宝安区福海街道和平社区同益新村东一巷8号","phone":"15712132108"},{"province":"广东省","city":"深圳市","area":"宝安区","name":"旭利邮政便民服务点","code":"518103","address":"深圳市宝安区福海街道桥头荔园路26号","phone":"13823378861"},{"province":"广东省","city":"深圳市","area":"宝安区","name":"春红邮政便民服务点","code":"518103","address":"深圳市宝安区福海街道新和社区二区十六巷6号104","phone":"15818560018"},{"province":"广东省","city":"深圳市","area":"宝安区","name":"仕泉邮政便民服务点","code":"518103","address":"深圳市宝安区福海街道塘尾社区塘尾十三区十三巷8－2号","phone":"13713862813"},{"province":"广东省","city":"深圳市","area":"宝安区","name":"旋风邮政便民服务点","code":"518103","address":"深圳市宝安区福海街道新和社区富桥三区一期宿舍B2栋101-105","phone":"18588430891"},{"province":"广东省","city":"深圳市","area":"宝安区","name":"恒之邮邮政便民服务点","code":"518103","address":"深圳市宝安区福海街道新和社区西一巷1-1号101","phone":"15817267469"},{"province":"广东省","city":"深圳市","area":"宝安区","name":"海军邮政便民服务点","code":"518103","address":"深圳市宝安区福海街道和平社区玻璃围新村北六巷15－1号","phone":"13713799577"},{"province":"广东省","city":"深圳市","area":"宝安区","name":"春红邮政便民服务点","code":"518103","address":"深圳市宝安区福海街道新和社区二区十六巷6号104","phone":"15818560018"},{"province":"广东省","city":"深圳市","area":"宝安区","name":"旭利邮政便民服务点","code":"518103","address":"深圳市宝安区福海街道桥头荔园路26号","phone":"13823378861"},{"province":"广东省","city":"深圳市","area":"宝安区","name":"宝丽邮政便民服务点","code":"518103","address":"深圳市宝安区福海街道稔田社区新区167号新区147号","phone":"13822607856"},{"province":"广东省","city":"深圳市","area":"宝安区","name":"兴旺邮政便民服务点","code":"518103","address":"深圳市宝安区福海街道和平社区同益新村东一巷8号","phone":"15712132108"},{"province":"广东省","city":"深圳市","area":"宝安区","name":"旭利邮政便民服务点","code":"518103","address":"深圳市宝安区福海街道桥头荔园路26号","phone":"13823378861"},{"province":"广东省","city":"深圳市","area":"宝安区","name":"春红邮政便民服务点","code":"518103","address":"深圳市宝安区福海街道新和社区二区十六巷6号104","phone":"15818560018"},{"province":"广东省","city":"深圳市","area":"宝安区","name":"仕泉邮政便民服务点","code":"518103","address":"深圳市宝安区福海街道塘尾社区塘尾十三区十三巷8－2号","phone":"13713862813"},{"province":"广东省","city":"深圳市","area":"宝安区","name":"旋风邮政便民服务点","code":"518103","address":"深圳市宝安区福海街道新和社区富桥三区一期宿舍B2栋101-105","phone":"18588430891"},{"province":"广东省","city":"深圳市","area":"宝安区","name":"恒之邮邮政便民服务点","code":"518103","address":"深圳市宝安区福海街道新和社区西一巷1-1号101","phone":"15817267469"},{"province":"广东省","city":"深圳市","area":"宝安区","name":"海军邮政便民服务点","code":"518103","address":"深圳市宝安区福海街道和平社区玻璃围新村北六巷15－1号","phone":"13713799577"},{"province":"广东省","city":"深圳市","area":"宝安区","name":"宝丽邮政便民服务点","code":"518103","address":"深圳市宝安区福海街道稔田社区新区167号新区147号","phone":"13822607856"},{"province":"广东省","city":"深圳市","area":"宝安区","name":"宝丽邮政便民服务点","code":"518103","address":"深圳市宝安区福海街道稔田社区新区167号新区147号","phone":"13822607856"},{"province":"广东省","city":"深圳市","area":"宝安区","name":"兴旺邮政便民服务点","code":"518103","address":"深圳市宝安区福海街道和平社区同益新村东一巷8号","phone":"15712132108"},{"province":"广东省","city":"深圳市","area":"宝安区","name":"旭利邮政便民服务点","code":"518103","address":"深圳市宝安区福海街道桥头荔园路26号","phone":"13823378861"},{"province":"广东省","city":"深圳市","area":"宝安区","name":"春红邮政便民服务点","code":"518103","address":"深圳市宝安区福海街道新和社区二区十六巷6号104","phone":"15818560018"},{"province":"广东省","city":"深圳市","area":"宝安区","name":"仕泉邮政便民服务点","code":"518103","address":"深圳市宝安区福海街道塘尾社区塘尾十三区十三巷8－2号","phone":"13713862813"},{"province":"广东省","city":"深圳市","area":"宝安区","name":"旭利邮政便民服务点","code":"518103","address":"深圳市宝安区福海街道桥头荔园路26号","phone":"13823378861"},{"province":"广东省","city":"深圳市","area":"宝安区","name":"恒之邮邮政便民服务点","code":"518103","address":"深圳市宝安区福海街道新和社区西一巷1-1号101","phone":"15817267469"},{"province":"广东省","city":"深圳市","area":"宝安区","name":"海军邮政便民服务点","code":"518103","address":"深圳市宝安区福海街道和平社区玻璃围新村北六巷15－1号","phone":"13713799577"},{"province":"广东省","city":"深圳市","area":"宝安区","name":"春红邮政便民服务点","code":"518103","address":"深圳市宝安区福海街道新和社区二区十六巷6号104","phone":"15818560018"},{"province":"广东省","city":"深圳市","area":"宝安区","name":"宝丽邮政便民服务点","code":"518103","address":"深圳市宝安区福海街道稔田社区新区167号新区147号","phone":"13822607856"},{"province":"广东省","city":"深圳市","area":"宝安区","name":"兴旺邮政便民服务点","code":"518103","address":"深圳市宝安区福海街道和平社区同益新村东一巷8号","phone":"15712132108"},{"province":"广东省","city":"深圳市","area":"宝安区","name":"旭利邮政便民服务点","code":"518103","address":"深圳市宝安区福海街道桥头荔园路26号","phone":"13823378861"},{"province":"广东省","city":"深圳市","area":"宝安区","name":"春红邮政便民服务点","code":"518103","address":"深圳市宝安区福海街道新和社区二区十六巷6号104","phone":"15818560018"},{"province":"广东省","city":"深圳市","area":"宝安区","name":"仕泉邮政便民服务点","code":"518103","address":"深圳市宝安区福海街道塘尾社区塘尾十三区十三巷8－2号","phone":"13713862813"},{"province":"广东省","city":"深圳市","area":"宝安区","name":"旋风邮政便民服务点","code":"518103","address":"深圳市宝安区福海街道新和社区富桥三区一期宿舍B2栋101-105","phone":"18588430891"},{"province":"广东省","city":"深圳市","area":"宝安区","name":"恒之邮邮政便民服务点","code":"518103","address":"深圳市宝安区福海街道新和社区西一巷1-1号101","phone":"15817267469"},{"province":"广东省","city":"深圳市","area":"宝安区","name":"海军邮政便民服务点","code":"518103","address":"深圳市宝安区福海街道和平社区玻璃围新村北六巷15－1号","phone":"13713799577"},{"province":"广东省","city":"深圳市","area":"宝安区","name":"仕泉邮政便民服务点","code":"518103","address":"深圳市宝安区福海街道塘尾社区塘尾十三区十三巷8－2号","phone":"13713862813"},{"province":"广东省","city":"深圳市","area":"宝安区","name":"旋风邮政便民服务点","code":"518103","address":"深圳市宝安区福海街道新和社区富桥三区一期宿舍B2栋101-105","phone":"18588430891"},{"province":"广东省","city":"深圳市","area":"宝安区","name":"宝丽邮政便民服务点","code":"518103","address":"深圳市宝安区福海街道稔田社区新区167号新区147号","phone":"13822607856"},{"province":"广东省","city":"深圳市","area":"宝安区","name":"兴旺邮政便民服务点","code":"518103","address":"深圳市宝安区福海街道和平社区同益新村东一巷8号","phone":"15712132108"},{"province":"广东省","city":"深圳市","area":"宝安区","name":"旭利邮政便民服务点","code":"518103","address":"深圳市宝安区福海街道桥头荔园路26号","phone":"13823378861"},{"province":"广东省","city":"深圳市","area":"宝安区","name":"春红邮政便民服务点","code":"518103","address":"深圳市宝安区福海街道新和社区二区十六巷6号104","phone":"15818560018"},{"province":"广东省","city":"深圳市","area":"宝安区","name":"仕泉邮政便民服务点","code":"518103","address":"深圳市宝安区福海街道塘尾社区塘尾十三区十三巷8－2号","phone":"13713862813"},{"province":"广东省","city":"深圳市","area":"宝安区","name":"恒之邮邮政便民服务点","code":"518103","address":"深圳市宝安区福海街道新和社区西一巷1-1号101","phone":"15817267469"},{"province":"广东省","city":"深圳市","area":"宝安区","name":"海军邮政便民服务点","code":"518103","address":"深圳市宝安区福海街道和平社区玻璃围新村北六巷15－1号","phone":"13713799577"},{"province":"广东省","city":"深圳市","area":"宝安区","name":"海军邮政便民服务点","code":"518103","address":"深圳市宝安区福海街道和平社区玻璃围新村北六巷15－1号","phone":"13713799577"},{"province":"广东省","city":"深圳市","area":"宝安区","name":"旋风邮政便民服务点","code":"518103","address":"深圳市宝安区福海街道新和社区富桥三区一期宿舍B2栋101-105","phone":"18588430891"},{"province":"广东省","city":"深圳市","area":"宝安区","name":"恒之邮邮政便民服务点","code":"518103","address":"深圳市宝安区福海街道新和社区西一巷1-1号101","phone":"15817267469"},{"province":"广东省","city":"深圳市","area":"宝安区","name":"海军邮政便民服务点","code":"518103","address":"深圳市宝安区福海街道和平社区玻璃围新村北六巷15－1号","phone":"13713799577"},{"province":"广东省","city":"深圳市","area":"宝安区","name":"恒之邮邮政便民服务点","code":"518103","address":"深圳市宝安区福海街道新和社区西一巷1-1号101","phone":"15817267469"},{"province":"广东省","city":"深圳市","area":"宝安区","name":"宝丽邮政便民服务点","code":"518103","address":"深圳市宝安区福海街道稔田社区新区167号新区147号","phone":"13822607856"},{"province":"广东省","city":"深圳市","area":"宝安区","name":"宝丽邮政便民服务点","code":"518103","address":"深圳市宝安区福海街道稔田社区新区167号新区147号","phone":"13822607856"},{"province":"广东省","city":"深圳市","area":"宝安区","name":"兴旺邮政便民服务点","code":"518103","address":"深圳市宝安区福海街道和平社区同益新村东一巷8号","phone":"15712132108"},{"province":"广东省","city":"深圳市","area":"宝安区","name":"旭利邮政便民服务点","code":"518103","address":"深圳市宝安区福海街道桥头荔园路26号","phone":"13823378861"},{"province":"广东省","city":"深圳市","area":"宝安区","name":"春红邮政便民服务点","code":"518103","address":"深圳市宝安区福海街道新和社区二区十六巷6号104","phone":"15818560018"},{"province":"广东省","city":"深圳市","area":"宝安区","name":"仕泉邮政便民服务点","code":"518103","address":"深圳市宝安区福海街道塘尾社区塘尾十三区十三巷8－2号","phone":"13713862813"},{"province":"广东省","city":"深圳市","area":"宝安区","name":"旋风邮政便民服务点","code":"518103","address":"深圳市宝安区福海街道新和社区富桥三区一期宿舍B2栋101-105","phone":"18588430891"},{"province":"广东省","city":"深圳市","area":"宝安区","name":"恒之邮邮政便民服务点","code":"518103","address":"深圳市宝安区福海街道新和社区西一巷1-1号101","phone":"15817267469"},{"province":"广东省","city":"深圳市","area":"宝安区","name":"海军邮政便民服务点","code":"518103","address":"深圳市宝安区福海街道和平社区玻璃围新村北六巷15－1号","phone":"13713799577"},{"province":"广东省","city":"深圳市","area":"宝安区","name":"兴旺邮政便民服务点","code":"518103","address":"深圳市宝安区福海街道和平社区同益新村东一巷8号","phone":"15712132108"},{"province":"广东省","city":"深圳市","area":"宝安区","name":"宝丽邮政便民服务点","code":"518103","address":"深圳市宝安区福海街道稔田社区新区167号新区147号","phone":"13822607856"},{"province":"广东省","city":"深圳市","area":"宝安区","name":"兴旺邮政便民服务点","code":"518103","address":"深圳市宝安区福海街道和平社区同益新村东一巷8号","phone":"15712132108"},{"province":"广东省","city":"深圳市","area":"宝安区","name":"旭利邮政便民服务点","code":"518103","address":"深圳市宝安区福海街道桥头荔园路26号","phone":"13823378861"},{"province":"广东省","city":"深圳市","area":"宝安区","name":"春红邮政便民服务点","code":"518103","address":"深圳市宝安区福海街道新和社区二区十六巷6号104","phone":"15818560018"},{"province":"广东省","city":"深圳市","area":"宝安区","name":"仕泉邮政便民服务点","code":"518103","address":"深圳市宝安区福海街道塘尾社区塘尾十三区十三巷8－2号","phone":"13713862813"},{"province":"广东省","city":"深圳市","area":"宝安区","name":"兴旺邮政便民服务点","code":"518103","address":"深圳市宝安区福海街道和平社区同益新村东一巷8号","phone":"15712132108"},{"province":"广东省","city":"深圳市","area":"宝安区","name":"旋风邮政便民服务点","code":"518103","address":"深圳市宝安区福海街道新和社区富桥三区一期宿舍B2栋101-105","phone":"18588430891"},{"province":"广东省","city":"深圳市","area":"宝安区","name":"海军邮政便民服务点","code":"518103","address":"深圳市宝安区福海街道和平社区玻璃围新村北六巷15－1号","phone":"13713799577"},{"province":"广东省","city":"深圳市","area":"宝安区","name":"恒之邮邮政便民服务点","code":"518103","address":"深圳市宝安区福海街道新和社区西一巷1-1号101","phone":"15817267469"},{"province":"广东省","city":"深圳市","area":"宝安区","name":"恒之邮邮政便民服务点","code":"518103","address":"深圳市宝安区福海街道新和社区西一巷1-1号101","phone":"15817267469"},{"province":"广东省","city":"深圳市","area":"宝安区","name":"海军邮政便民服务点","code":"518103","address":"深圳市宝安区福海街道和平社区玻璃围新村北六巷15－1号","phone":"13713799577"}]