[{"province":"广东省","city":"东莞市","area":"东莞县","name":"东莞市石排镇石兴邮政所","code":"523338","address":"广东东莞市石排镇埔心三路13-17号","phone":"0769-86653064"},{"province":"广东省","city":"东莞市","area":"东莞县","name":"东莞市石排镇石兴邮政所","code":"523338","address":"广东东莞市石排镇埔心三路13-17号","phone":"0769-86653064"},{"province":"广东省","city":"东莞市","area":"东莞县","name":"东莞市石排镇石兴邮政所","code":"523338","address":"广东东莞市石排镇埔心三路13-17号","phone":"0769-86653064"},{"province":"广东省","city":"东莞市","area":"东莞县","name":"东莞市石排镇石兴邮政所","code":"523338","address":"广东东莞市石排镇埔心三路13-17号","phone":"0769-86653064"},{"province":"广东省","city":"东莞市","area":"东莞县","name":"东莞市石排镇石兴邮政所","code":"523338","address":"广东东莞市石排镇埔心三路13-17号","phone":"0769-86653064"},{"province":"广东省","city":"东莞市","area":"东莞县","name":"东莞市石排镇石兴邮政所","code":"523338","address":"广东东莞市石排镇埔心三路13-17号","phone":"0769-86653064"},{"province":"广东省","city":"东莞市","area":"东莞县","name":"东莞市石排镇石兴邮政所","code":"523338","address":"广东东莞市石排镇埔心三路13-17号","phone":"0769-86653064"},{"province":"广东省","city":"东莞市","area":"东莞县","name":"东莞市石排镇石兴邮政所","code":"523338","address":"广东东莞市石排镇埔心三路13-17号","phone":"0769-86653064"},{"province":"广东省","city":"东莞市","area":"东莞县","name":"东莞市石排镇石兴邮政所","code":"523338","address":"广东东莞市石排镇埔心三路13-17号","phone":"0769-86653064"},{"province":"广东省","city":"东莞市","area":"东莞县","name":"东莞市石排镇石兴邮政所","code":"523338","address":"广东东莞市石排镇埔心三路13-17号","phone":"0769-86653064"},{"province":"广东省","city":"东莞市","area":"东莞县","name":"东莞市石排镇石兴邮政所","code":"523338","address":"广东东莞市石排镇埔心三路13-17号","phone":"0769-86653064"},{"province":"广东省","city":"东莞市","area":"东莞县","name":"东莞市石排镇石兴邮政所","code":"523338","address":"广东东莞市石排镇埔心三路13-17号","phone":"0769-86653064"},{"province":"广东省","city":"东莞市","area":"东莞县","name":"东莞市石排镇石兴邮政所","code":"523338","address":"广东东莞市石排镇埔心三路13-17号","phone":"0769-86653064"},{"province":"广东省","city":"东莞市","area":"东莞县","name":"东莞市石排镇石兴邮政所","code":"523338","address":"广东东莞市石排镇埔心三路13-17号","phone":"0769-86653064"},{"province":"广东省","city":"东莞市","area":"东莞县","name":"东莞市石排镇石兴邮政所","code":"523338","address":"广东东莞市石排镇埔心三路13-17号","phone":"0769-86653064"},{"province":"广东省","city":"东莞市","area":"东莞县","name":"东莞市石排镇石兴邮政所","code":"523338","address":"广东东莞市石排镇埔心三路13-17号","phone":"0769-86653064"},{"province":"广东省","city":"东莞市","area":"东莞县","name":"东莞市石排镇石兴邮政所","code":"523338","address":"广东东莞市石排镇埔心三路13-17号","phone":"0769-86653064"},{"province":"广东省","city":"东莞市","area":"东莞县","name":"东莞市石排镇石兴邮政所","code":"523338","address":"广东东莞市石排镇埔心三路13-17号","phone":"0769-86653064"},{"province":"广东省","city":"东莞市","area":"东莞县","name":"东莞市石排镇石兴邮政所","code":"523338","address":"广东东莞市石排镇埔心三路13-17号","phone":"0769-86653064"},{"province":"广东省","city":"东莞市","area":"东莞县","name":"东莞市石排镇石兴邮政所","code":"523338","address":"广东东莞市石排镇埔心三路13-17号","phone":"0769-86653064"},{"province":"广东省","city":"东莞市","area":"东莞县","name":"东莞市石排镇石兴邮政所","code":"523338","address":"广东东莞市石排镇埔心三路13-17号","phone":"0769-86653064"},{"province":"广东省","city":"东莞市","area":"东莞县","name":"东莞市石排镇石兴邮政所","code":"523338","address":"广东东莞市石排镇埔心三路13-17号","phone":"0769-86653064"},{"province":"广东省","city":"东莞市","area":"东莞县","name":"东莞市石排镇石兴邮政所","code":"523338","address":"广东东莞市石排镇埔心三路13-17号","phone":"0769-86653064"},{"province":"广东省","city":"东莞市","area":"东莞县","name":"东莞市石排镇石兴邮政所","code":"523338","address":"广东东莞市石排镇埔心三路13-17号","phone":"0769-86653064"}]