[{"province":"广东省","city":"佛山市","area":"顺德区","name":"佛山市顺德区陈村邮政营业所","code":"528313","address":"东佛山市顺德区陈村镇永宁路1号","phone":"0757-23338403"},{"province":"广东省","city":"佛山市","area":"顺德区","name":"佛山市顺德区陈村邮政营业所","code":"528313","address":"东佛山市顺德区陈村镇永宁路1号","phone":"0757-23338403"},{"province":"广东省","city":"佛山市","area":"顺德区","name":"佛山市顺德区陈村邮政营业所","code":"528313","address":"东佛山市顺德区陈村镇永宁路1号","phone":"0757-23338403"},{"province":"广东省","city":"佛山市","area":"顺德区","name":"佛山市顺德区陈村邮政营业所","code":"528313","address":"东佛山市顺德区陈村镇永宁路1号","phone":"0757-23338403"},{"province":"广东省","city":"佛山市","area":"顺德区","name":"佛山市顺德区陈村邮政营业所","code":"528313","address":"东佛山市顺德区陈村镇永宁路1号","phone":"0757-23338403"}]