[{"province":"广西壮族自治区","city":"南宁市","area":"横县","name":"横县大厦邮政所","code":"530399","address":"横县横州镇魁星路10号","phone":"0771-7222000"},{"province":"广西壮族自治区","city":"南宁市","area":"横县","name":"横县城东邮政所","code":"530399","address":"","phone":"0771-7233770"},{"province":"广西壮族自治区","city":"南宁市","area":"横县","name":"横县洪德邮政所","code":"530399","address":"横县横州镇洪德路41号","phone":"0771-7222425"},{"province":"广西壮族自治区","city":"南宁市","area":"横县","name":"横县城东邮政所","code":"530399","address":"","phone":"0771-7233770"},{"province":"广西壮族自治区","city":"南宁市","area":"横县","name":"横县洪德邮政所","code":"530399","address":"横县横州镇洪德路41号","phone":"0771-7222425"},{"province":"广西壮族自治区","city":"南宁市","area":"横县","name":"横县大厦邮政所","code":"530399","address":"横县横州镇魁星路10号","phone":"0771-7222000"},{"province":"广西壮族自治区","city":"南宁市","area":"横县","name":"横县城东邮政所","code":"530399","address":"","phone":"0771-7233770"},{"province":"广西壮族自治区","city":"南宁市","area":"横县","name":"横县大厦邮政所","code":"530399","address":"横县横州镇魁星路10号","phone":"0771-7222000"},{"province":"广西壮族自治区","city":"南宁市","area":"横县","name":"横县洪德邮政所","code":"530399","address":"横县横州镇洪德路41号","phone":"0771-7222425"}]