[{"province":"广西壮族自治区","city":"河池市","area":"金城江区","name":"火车站邮政支局","code":"547099","address":"河池市金城江区解放东路1号","phone":"0778-2283740"},{"province":"广西壮族自治区","city":"河池市","area":"金城江区","name":"城东邮政所","code":"547099","address":"广西河池市金城江区城东路","phone":"0778-2303519"},{"province":"广西壮族自治区","city":"河池市","area":"金城江区","name":"河池高级中学邮政所","code":"547099","address":"河池市金城江区教育路105号（河池高中园内第11栋一楼）","phone":"0778-2110969"},{"province":"广西壮族自治区","city":"河池市","area":"金城江区","name":"工农路邮政支局","code":"547099","address":"河池市金城江区工农路176号","phone":"0778-2282529"},{"province":"广西壮族自治区","city":"河池市","area":"金城江区","name":"城东邮政所","code":"547099","address":"广西河池市金城江区城东路","phone":"0778-2303519"},{"province":"广西壮族自治区","city":"河池市","area":"金城江区","name":"工农路邮政支局","code":"547099","address":"河池市金城江区工农路176号","phone":"0778-2282529"},{"province":"广西壮族自治区","city":"河池市","area":"金城江区","name":"工农路邮政支局","code":"547099","address":"河池市金城江区工农路176号","phone":"0778-2282529"},{"province":"广西壮族自治区","city":"河池市","area":"金城江区","name":"城东邮政所","code":"547099","address":"广西河池市金城江区城东路","phone":"0778-2303519"}]