[{"province":"海南省","city":"海口市","area":"秀英区","name":"秀英邮政支局","code":"570311","address":"海南省海口市秀英区秀英街道办事处海秀西路44号","phone":"0898-68662173"},{"province":"海南省","city":"海口市","area":"秀英区","name":"滨海大道邮政支局","code":"570311","address":"海南省海口市秀英区海秀街道办丘海大道4号","phone":"0898-68664678"},{"province":"海南省","city":"海口市","area":"秀英区","name":"南海大道邮政所","code":"570311","address":"海南省海口市秀英区秀英街道办事处南海大道143号","phone":"15008971569"},{"province":"海南省","city":"海口市","area":"秀英区","name":"万秀路邮政所","code":"570311","address":"海南省海口市秀英区秀英街道办事处万秀路邮政汽修厂临街铺面","phone":"0898-68663087"}]