[{"province":"四川省","city":"成都市","area":"蒲江县","name":"驭虹路邮政支局","code":"611630","address":"四川省成都市蒲江县鹤山街道驭虹路76号附4号、76号附5号、76号附6号、76号附7号、76号附8号、76号附9号","phone":"028-88550014"},{"province":"四川省","city":"成都市","area":"蒲江县","name":"朝阳湖邮政所","code":"611630","address":"四川省成都市蒲江县朝阳湖镇温泉路187号","phone":"19136290032"},{"province":"四川省","city":"成都市","area":"蒲江县","name":"白云邮政所","code":"611630","address":"四川省成都市蒲江县朝阳湖镇白云村朝阳路53号","phone":"18380284598"},{"province":"四川省","city":"成都市","area":"蒲江县","name":"光明邮政所（暂停）","code":"611630","address":"四川省成都市蒲江县","phone":"13668218747"}]