[{"province":"四川省","city":"凉山彝族自治州","area":"西昌市","name":"西昌市西客站邮政支局","code":"615099","address":"四川省凉山州西昌市长安西路","phone":"18096287797"},{"province":"四川省","city":"凉山彝族自治州","area":"西昌市","name":"西昌市西客站邮政支局","code":"615099","address":"四川省凉山州西昌市长安西路","phone":"18096287797"},{"province":"四川省","city":"凉山彝族自治州","area":"西昌市","name":"西昌市西客站邮政支局","code":"615099","address":"四川省凉山州西昌市长安西路","phone":"18096287797"},{"province":"四川省","city":"凉山彝族自治州","area":"西昌市","name":"西昌市西客站邮政支局","code":"615099","address":"四川省凉山州西昌市长安西路","phone":"18096287797"},{"province":"四川省","city":"凉山彝族自治州","area":"西昌市","name":"西昌市西客站邮政支局","code":"615099","address":"四川省凉山州西昌市长安西路","phone":"18096287797"}]