[{"province":"四川省","city":"凉山彝族自治州","area":"布拖县","name":"美撒邮政所","code":"616351","address":"四川省凉山彝族自治州布拖县拖觉镇美撒村","phone":"19915711281"},{"province":"四川省","city":"凉山彝族自治州","area":"布拖县","name":"觉撒邮政所","code":"616351","address":"四川省凉山彝族自治州布拖县拖觉镇博作村六组","phone":"15984967382"},{"province":"四川省","city":"凉山彝族自治州","area":"布拖县","name":"拖觉邮政所","code":"616351","address":"四川省凉山彝族自治州布拖县拖觉镇菲土鲁村汽车客运站","phone":"15308154567"},{"province":"四川省","city":"凉山彝族自治州","area":"布拖县","name":"补尔邮政所","code":"616351","address":"四川省凉山州布拖县补尔乡竹尔苦村","phone":"19983872933"},{"province":"四川省","city":"凉山彝族自治州","area":"布拖县","name":"洛古邮政所","code":"616351","address":"四川省凉山彝族自治州布拖县拖觉镇阿保村","phone":"18113319984"},{"province":"四川省","city":"凉山彝族自治州","area":"布拖县","name":"乌依邮政所","code":"616351","address":"四川省凉山彝族自治州布拖县拉果乡乌依村","phone":"19983872953"},{"province":"四川省","city":"凉山彝族自治州","area":"布拖县","name":"拉果邮政所","code":"616351","address":"四川省凉山州布拖县拉果乡","phone":"15283445223"},{"province":"四川省","city":"凉山彝族自治州","area":"布拖县","name":"浪珠邮政所","code":"616351","address":"四川省凉山彝族自治州布拖县","phone":"19949625134"}]