[{"province":"四川省","city":"凉山彝族自治州","area":"美姑县","name":"候播乃拖邮政所","code":"616452","address":"四川省凉山州美姑县候播乃拖乡场镇","phone":"15282938052"},{"province":"四川省","city":"凉山彝族自治州","area":"美姑县","name":"采红邮政所","code":"616452","address":"四川省凉山彝族自治州美姑县候古莫镇采红村","phone":"13981538022"},{"province":"四川省","city":"凉山彝族自治州","area":"美姑县","name":"九口邮政所","code":"616452","address":"四川省凉山州美姑县九口乡场镇","phone":"18328889704"},{"province":"四川省","city":"凉山彝族自治州","area":"美姑县","name":"苏洛邮政所","code":"616452","address":"四川省凉山彝族自治州美姑县候播乃拖乡苏洛村","phone":"18228717177"}]