[{"province":"四川省","city":"眉山市","area":"青神县","name":"青衣大道邮政支局","code":"620460","address":"四川省眉山市青神县青竹街道青衣大道295号","phone":"028-38817509"},{"province":"四川省","city":"眉山市","area":"青神县","name":"城北路邮政所","code":"620460","address":"四川省眉山市青神县青竹街道城北路107号","phone":"15328771130"},{"province":"四川省","city":"眉山市","area":"青神县","name":"大西街邮政支局","code":"620460","address":"四川省眉山市青神县青竹街道大西街7号","phone":"028-38811450"},{"province":"四川省","city":"眉山市","area":"青神县","name":"西龙邮政支局","code":"620460","address":"四川省眉山市青神县西龙镇锦绣大道37、39、41号","phone":"028-35081890"},{"province":"四川省","city":"眉山市","area":"青神县","name":"高台邮政支局","code":"620460","address":"四川省眉山市青神县高台镇建设路22-24号","phone":"028-35081893"},{"province":"四川省","city":"眉山市","area":"青神县","name":"河坝子邮政支局","code":"620460","address":"四川省眉山市青神县高台镇河坝子社区玉蟾街63号","phone":"028-35081892"},{"province":"四川省","city":"眉山市","area":"青神县","name":"罗波邮政支局","code":"620460","address":"四川省眉山市青神县罗波乡新建街11号","phone":"028-35081895"},{"province":"四川省","city":"眉山市","area":"青神县","name":"青竹街道兰沟村邮政所","code":"620460","address":"四川省眉山市青神县青竹街道竹艺街11号","phone":"13778860277"},{"province":"四川省","city":"眉山市","area":"青神县","name":"白果邮政所","code":"620460","address":"四川省眉山市青神县白果乡甘家沟村1组","phone":"18990383118"},{"province":"四川省","city":"眉山市","area":"青神县","name":"瑞峰邮政所","code":"620460","address":"四川省眉山市青神县瑞峰镇北街10号","phone":"13378361072"}]