[{"province":"四川省","city":"眉山市","area":"仁寿县","name":"汪洋邮政支局","code":"620587","address":"四川省眉山市仁寿县汪洋镇八一街128号、130号、132号、134号","phone":"028-36502843"},{"province":"四川省","city":"眉山市","area":"仁寿县","name":"四公邮政支局","code":"620587","address":"四川省眉山市仁寿县汪洋镇四公社区平安街97-101号","phone":"028-36290007"},{"province":"四川省","city":"眉山市","area":"仁寿县","name":"四公邮政所","code":"620587","address":"四川省眉山市仁寿县汪洋镇四公社区平安街105号","phone":"13568242996"},{"province":"四川省","city":"眉山市","area":"仁寿县","name":"松峰邮政所","code":"620587","address":"四川省眉山市仁寿县汪洋镇碧云村仁义街62号","phone":"15196469456"},{"province":"四川省","city":"眉山市","area":"仁寿县","name":"汪洋邮政所","code":"620587","address":"四川省眉山市仁寿县汪洋镇古井街90号","phone":"18990314069"},{"province":"四川省","city":"眉山市","area":"仁寿县","name":"永宁邮政所","code":"620587","address":"四川省眉山市仁寿县汪洋镇永宁街道369-371号","phone":"15892707390"},{"province":"四川省","city":"眉山市","area":"仁寿县","name":"涂家邮政所","code":"620587","address":"四川省眉山市仁寿县汪洋镇涂家社区新横街8号、10号","phone":"13350708838"},{"province":"四川省","city":"眉山市","area":"仁寿县","name":"大洪邮政所","code":"620587","address":"四川省眉山市仁寿县汪洋镇大洪村8组79号","phone":"15328767269"}]