[{"province":"四川省","city":"甘孜藏族自治州","area":"石渠县","name":"石渠县洛须邮政支局","code":"627354","address":"四川省甘孜藏族自治州石渠县洛须镇洛须村","phone":"0836-8623616"},{"province":"四川省","city":"甘孜藏族自治州","area":"石渠县","name":"石渠县奔达邮政代办所","code":"627354","address":"四川省甘孜藏族自治州石渠县奔达乡","phone":"0836-8622019"},{"province":"四川省","city":"甘孜藏族自治州","area":"石渠县","name":"石渠县麻呷邮政代办所","code":"627354","address":"四川省甘孜藏族自治州石渠县麻呷乡","phone":"0836-8622019"},{"province":"四川省","city":"甘孜藏族自治州","area":"石渠县","name":"石渠县奔达邮政代办所","code":"627354","address":"四川省甘孜藏族自治州石渠县奔达乡","phone":"0836-8622019"},{"province":"四川省","city":"甘孜藏族自治州","area":"石渠县","name":"石渠县洛须邮政支局","code":"627354","address":"四川省甘孜藏族自治州石渠县洛须镇洛须村","phone":"0836-8623616"},{"province":"四川省","city":"甘孜藏族自治州","area":"石渠县","name":"石渠县奔达邮政代办所","code":"627354","address":"四川省甘孜藏族自治州石渠县奔达乡","phone":"0836-8622019"}]