[{"province":"四川省","city":"南充市","area":"仪陇县","name":"新政邮政所","code":"637676","address":"四川省南充市仪陇县新政镇琳琅大道26号","phone":"0817-7210685"},{"province":"四川省","city":"南充市","area":"仪陇县","name":"德龙广场邮政支局","code":"637676","address":"四川省南充市仪陇县新政镇宏德大道中段1号","phone":"0817-7210356"},{"province":"四川省","city":"南充市","area":"仪陇县","name":"宏德大道邮政支局","code":"637676","address":"四川省南充市仪陇县宏德大道1号","phone":"13990831997"},{"province":"四川省","city":"南充市","area":"仪陇县","name":"紫东路邮政所","code":"637676","address":"四川省南充市仪陇县新政镇紫东街159-163","phone":"0817-7233680"}]