[{"province":"四川省","city":"广安市","area":"广安区","name":"广福邮政支局","code":"638099","address":"四川省广安市广安区万盛街道金安大道二段118号","phone":"0826-2347617"},{"province":"四川省","city":"广安市","area":"广安区","name":"万盛街邮政支局","code":"638099","address":"四川省广安市广安区万盛街道万新一街22号","phone":"0826-2392652"},{"province":"四川省","city":"广安市","area":"广安区","name":"广宁南路邮政支局","code":"638099","address":"四川省广安市广安区广福街道广宁南路1号（邮储银行100米内）","phone":"0826-2367133"},{"province":"四川省","city":"广安市","area":"广安区","name":"宏志大道邮政支局","code":"638099","address":"四川省广安市广安区中桥街道宏志大道717号","phone":"0826-2344216"},{"province":"四川省","city":"广安市","area":"广安区","name":"西溪路邮政支局","code":"638099","address":"四川省广安市广安区广福街道西溪路85号","phone":"0826-2249128"},{"province":"四川省","city":"广安市","area":"广安区","name":"方坪邮政所","code":"638099","address":"四川省广安市广安区官盛镇新民街7号","phone":"15082658528"},{"province":"四川省","city":"广安市","area":"广安区","name":"官盛邮政所","code":"638099","address":"四川省广安市广安区官盛镇兴盛街40号","phone":"13608270793"},{"province":"四川省","city":"广安市","area":"前锋区","name":"奎阁邮政所","code":"638099","address":"四川省广安市前锋区广安经济技术开发区奎阁街道奎阁大道11号4号、5号","phone":"15282684000"}]