[{"province":"四川省","city":"广安市","area":"武胜县","name":"武胜县鸣钟邮政所","code":"638414","address":"四川省武胜县鸣钟乡金钟街242号","phone":"0826-6206030"},{"province":"四川省","city":"广安市","area":"武胜县","name":"武胜县鸣钟邮政所","code":"638414","address":"四川省武胜县鸣钟乡金钟街242号","phone":"0826-6206030"},{"province":"四川省","city":"广安市","area":"武胜县","name":"武胜县鸣钟邮政所","code":"638414","address":"四川省武胜县鸣钟乡金钟街242号","phone":"0826-6206030"},{"province":"四川省","city":"广安市","area":"武胜县","name":"武胜县鸣钟邮政所","code":"638414","address":"四川省武胜县鸣钟乡金钟街242号","phone":"0826-6206030"}]