[{"province":"河北省","city":"承德市","area":"滦平县","name":"火斗山邮政代办所","code":"68254","address":"河北省承德市滦平县火斗山乡火斗山村","phone":"18831482398"},{"province":"河北省","city":"承德市","area":"滦平县","name":"滦平县巴克什营支局","code":"68254","address":"滦平县巴克什营镇巴克什营村","phone":"0314-8838086"},{"province":"河北省","city":"承德市","area":"滦平县","name":"滦平县巴克什营支局","code":"68254","address":"滦平县巴克什营镇巴克什营村","phone":"0314-8838086"},{"province":"河北省","city":"承德市","area":"滦平县","name":"滦平县巴克什营支局","code":"68254","address":"滦平县巴克什营镇巴克什营村","phone":"0314-8838086"}]