[{"province":"陕西省","city":"汉中市","area":"镇巴县","name":"河滨邮政支局","code":"723600","address":"陕西省汉中市镇巴县河滨路桥头泾洋街道办河滨路桥头","phone":"15891677186"},{"province":"陕西省","city":"汉中市","area":"镇巴县","name":"车站邮政支局","code":"723600","address":"陕西省汉中市镇巴县汽车站旁边泾洋街道办汽车站旁边","phone":"18291687399"},{"province":"陕西省","city":"汉中市","area":"镇巴县","name":"新城街邮政支局","code":"723600","address":"陕西省汉中市镇巴县泾洋街道办泾洋街道办秦茗路秦茗路口","phone":"13310967528"},{"province":"陕西省","city":"汉中市","area":"镇巴县","name":"小洋镇邮政支局","code":"723600","address":"陕西省汉中市镇巴县小洋镇小洋村小洋镇小洋村街上","phone":"15309168968"}]