[{"province":"陕西省","city":"汉中市","area":"镇巴县","name":"赤北邮政支局","code":"723612","address":"陕西省汉中市镇巴县简池镇简池镇简池村街上小组","phone":"15029865589"},{"province":"陕西省","city":"汉中市","area":"镇巴县","name":"三溪邮政所","code":"723612","address":"陕西省汉中市镇巴县简池镇三溪乡简池镇三溪乡安全社区街上","phone":"13992641269"},{"province":"陕西省","city":"汉中市","area":"镇巴县","name":"大池邮政所","code":"723612","address":"陕西省汉中市镇巴县大池镇大池坝社区街上","phone":"13484993128"},{"province":"陕西省","city":"汉中市","area":"镇巴县","name":"永乐邮政所","code":"723612","address":"陕西省汉中市镇巴县永乐镇永乐镇核桃树社区街上小组","phone":"13891667503"}]