[{"province":"甘肃省","city":"兰州市","area":"安宁区","name":"费家营邮政支局","code":"730070","address":"甘肃省兰州市安宁区安宁西路596号","phone":"0931-7668487"},{"province":"甘肃省","city":"兰州市","area":"安宁区","name":"安宁西路邮政支局","code":"730070","address":"甘肃省兰州市安宁区安宁西路852号","phone":"0931-7781264"},{"province":"甘肃省","city":"兰州市","area":"安宁区","name":"安宁东路邮政支局","code":"730070","address":"甘肃省兰州市安宁区安宁东路244号附2号商铺","phone":"0931-7756339"},{"province":"甘肃省","city":"兰州市","area":"安宁区","name":"营门村邮政所","code":"730070","address":"甘肃省兰州市安宁营门村1号","phone":"0931-7630811"},{"province":"甘肃省","city":"兰州市","area":"安宁区","name":"十里店邮政支局","code":"730070","address":"甘肃省兰州市安宁区安宁东路441号","phone":"0931-7766039"},{"province":"甘肃省","city":"兰州市","area":"安宁区","name":"安宁西路邮政支局","code":"730070","address":"甘肃省兰州市安宁区安宁西路852号","phone":"0931-7781264"},{"province":"甘肃省","city":"兰州市","area":"安宁区","name":"安宁东路邮政支局","code":"730070","address":"甘肃省兰州市安宁区安宁东路244号附2号商铺","phone":"0931-7756339"},{"province":"甘肃省","city":"兰州市","area":"安宁区","name":"营门村邮政所","code":"730070","address":"甘肃省兰州市安宁营门村1号","phone":"0931-7630811"},{"province":"甘肃省","city":"兰州市","area":"安宁区","name":"十里店邮政支局","code":"730070","address":"甘肃省兰州市安宁区安宁东路441号","phone":"0931-7766039"}]