[{"province":"甘肃省","city":"武威市","area":"凉州区","name":"四十里邮政所","code":"733015","address":"甘肃省武威市凉州区永丰镇四十里村","phone":"13830531382"},{"province":"甘肃省","city":"武威市","area":"凉州区","name":"四十里邮政所","code":"733015","address":"甘肃省武威市凉州区永丰镇四十里村","phone":"13830531382"},{"province":"甘肃省","city":"武威市","area":"凉州区","name":"四十里邮政所","code":"733015","address":"甘肃省武威市凉州区永丰镇四十里村","phone":"13830531382"},{"province":"甘肃省","city":"武威市","area":"凉州区","name":"四十里邮政所","code":"733015","address":"甘肃省武威市凉州区永丰镇四十里村","phone":"13830531382"},{"province":"甘肃省","city":"武威市","area":"凉州区","name":"四十里邮政所","code":"733015","address":"甘肃省武威市凉州区永丰镇四十里村","phone":"13830531382"}]