[{"province":"青海省","city":"西宁市","area":"城东区","name":"互助中路邮政所","code":"810006","address":"西宁市互助中路191——7号","phone":"0971-8083523"},{"province":"青海省","city":"西宁市","area":"城东区","name":"互助西路邮政所","code":"810006","address":"青海省西宁市城东区互助西路1号","phone":"0971-6110083"},{"province":"青海省","city":"西宁市","area":"城东区","name":"东市场邮政所","code":"810006","address":"西宁市互助西路196号","phone":"0971-8136272"},{"province":"青海省","city":"西宁市","area":"城东区","name":"互助西路邮政所","code":"810006","address":"青海省西宁市城东区互助西路1号","phone":"0971-6110083"},{"province":"青海省","city":"西宁市","area":"城东区","name":"东关大街邮政支局","code":"810006","address":"西宁市东关大街152号","phone":"0971-8131200"},{"province":"青海省","city":"西宁市","area":"城东区","name":"东关大街邮政支局","code":"810006","address":"西宁市东关大街152号","phone":"0971-8131200"},{"province":"青海省","city":"西宁市","area":"城东区","name":"东关大街邮政支局","code":"810006","address":"西宁市东关大街152号","phone":"0971-8131200"},{"province":"青海省","city":"西宁市","area":"城东区","name":"东市场邮政所","code":"810006","address":"西宁市互助西路196号","phone":"0971-8136272"},{"province":"青海省","city":"西宁市","area":"城东区","name":"互助路邮政支局","code":"810006","address":"西宁市七一路延伸段18号","phone":"0971-8149657"},{"province":"青海省","city":"西宁市","area":"城东区","name":"南小街邮政所","code":"810006","address":"西宁市南小街32——6号","phone":"0971-8130781"}]